README.rst
setup.py
ckanext/__init__.py
ckanext/openspending/__init__.py
ckanext/openspending/exceptions.py
ckanext/openspending/plugin.py
ckanext_openspending.egg-info/PKG-INFO
ckanext_openspending.egg-info/SOURCES.txt
ckanext_openspending.egg-info/dependency_links.txt
ckanext_openspending.egg-info/entry_points.txt
ckanext_openspending.egg-info/namespace_packages.txt
ckanext_openspending.egg-info/not-zip-safe
ckanext_openspending.egg-info/requires.txt
ckanext_openspending.egg-info/top_level.txt