Metadata-Version: 1.1
Name: ckanext-openspending
Version: 0.1.0
Summary: Automatically model and submit budgets to the OpenSpending
Home-page: https://github.com/tryggvib/ckanext-openspending
Author: Tryggvi Bjorgvinsson
Author-email: tryggvi.bjorgvinsson@okfn.org
License: AGPLv3
Keywords: ckan openspending
Platform: UNKNOWN
Classifier: Development Status :: 4 - Beta
Classifier: Intended Audience :: Other Audience
Classifier: License :: OSI Approved :: GNU Affero General Public License v3
Classifier: Programming Language :: Python :: 2.7
Classifier: Topic :: Internet :: WWW/HTTP :: Dynamic Content
